{
    "country": "DEU_Germany/",
    "region": "WMO_Region_6_Europe/",
    "province_map": {
        "NW": "NW_Nordrhein-Westfalen/",
        "BE": "BE_Berlin/",
        "MV": "MV_Mecklenburg-Vorpommern/",
        "BW": "BW_Baden-Wurttemberg/",
        "NI": "NI_Niedersachsen/",
        "HH": "HH_Hamburg/",
        "SN": "SN_Sachsen/",
        "BY": "BY_Bayern/",
        "RP": "RP_Rheinland-Pfalz/",
        "BB": "BB_Brandenburg/",
        "SL": "SL_Saarland/",
        "HE": "HE_Hessen/",
        "SH": "SH_Schleswig-Holstein/",
        "HB": "HB_Bremen/",
        "TH": "TH_Thuringen/",
        "ST": "ST_Sachsen-Anhalt/"
    },
    "file_list": [
        "DEU_NW_Dusseldorf.AP.104000_TMYx.2009-2023.zip",
        "DEU_BE_Berlin-Schonefeld.AP.103850_TMYx.zip",
        "DEU_MV_Teterow.101770_TMYx.zip",
        "DEU_NW_Soest.104264_TMYx.zip",
        "DEU_BW_Friedrichshafen.AP.109350_TMYx.2007-2021.zip",
        "DEU_NI_Wangerogge.Island.101230_TMYx.zip",
        "DEU_HH_Hamburg.Finkenwerder.AP.101490_TMYx.2009-2023.zip",
        "DEU_SN_Leipzig.Holzhausen.104710_TMYx.2007-2021.zip",
        "DEU_BY_Roth.AP.107650_TMYx.zip",
        "DEU_RP_Deuselbach.106150_TMYx.zip",
        "DEU_NW_Gutersloh.AP.103200_TMYx.zip",
        "DEU_NW_Siegerland.AP.106162_TMYx.2007-2021.zip",
        "DEU_BB_Holzdorf.AB.104760_TMYx.2007-2021.zip",
        "DEU_HH_Hamburg.Finkenwerder.AP.101490_TMYx.zip",
        "DEU_NW_Paderborn.Lippstadt.AP.104260_TMYx.2009-2023.zip",
        "DEU_RP_Buchel.AB.106130_TMYx.2007-2021.zip",
        "DEU_SL_Saarbrucken.AP.107080_TMYx.zip",
        "DEU_SN_Chemnitz-Stelzendorf_105770_TRY2035_09_Jahr_BBSR.zip",
        "DEU_BY_Nurnberg.AP.107630_TMYx.2009-2023.zip",
        "DEU_BY_Garmisch-Partenkirchen_109630_TRY2010_15_Somm_BBSR.zip",
        "DEU_NI_Oldenburg.102150_TMYx.zip",
        "DEU_NW_Monchengladbach.AP.104374_TMYx.zip",
        "DEU_NW_Essen_104100_TRY2035_05_Jahr_BBSR.zip",
        "DEU_BW_Donaueschingen-Villingen.AP.109120_TMYx.2007-2021.zip",
        "DEU_BY_Hof_106850_TRY2010_10_Jahr_BBSR.zip",
        "DEU_BB_Potsdam_103790_TRY2035_04_Wint_BBSR.zip",
        "DEU_NW_Rheine.Bentlage.AP.103060_TMYx.2007-2021.zip",
        "DEU_HE_Wiesbaden.AB.106330_TMYx.zip",
        "DEU_BW_Lahr-Schwarzwald.AP.108050_TMYx.2009-2023.zip",
        "DEU_BB_Holzdorf.AB.104760_TMYx.2009-2023.zip",
        "DEU_SH_Leck.AP.100220_TMYx.2007-2021.zip",
        "DEU_SH_Hohn.AB.100380_TMYx.2004-2018.zip",
        "DEU_SN_Fichtelberg_105780_TRY2010_11_Wint_BBSR.zip",
        "DEU_BY_Altenstadt.AP.109540_TMYx.2004-2018.zip",
        "DEU_BB_Holzdorf.AB.104760_TMYx.2004-2018.zip",
        "DEU_BW_Messstetten.108270_TMYx.2007-2021.zip",
        "DEU_HE_Frankfurt.AP.106370_TMYx.2004-2018.zip",
        "DEU_SH_Fehmar.100550_TMYx.2004-2018.zip",
        "DEU_HE_Frankfurt.AP.106370_TMYx.2007-2021.zip",
        "DEU_HB_Bremerhaven.101290_TMYx.zip",
        "DEU_MV_Neubrandenburg.Trollenhagen.AP.102810_TMYx.2009-2023.zip",
        "DEU_NW_Achum.Buckeburg.AB.103350_TMYx.2004-2018.zip",
        "DEU_SH_Doernick.101500_TMYx.2007-2021.zip",
        "DEU_HE_Giessen-Wettenberg.105320_TMYx.zip",
        "DEU_NW_Kalkar.104040_TMYx.2007-2021.zip",
        "DEU_NW_Kalkar.104040_TMYx.2004-2018.zip",
        "DEU_NW_Essen_104100_TRY2010_05_Jahr_BBSR.zip",
        "DEU_BY_Muhldorf.am.Inn_108750_TRY2010_13_Jahr_BBSR.zip",
        "DEU_NW_Monchengladbach.AP.104374_TMYx.2004-2018.zip",
        "DEU_TH_Altenburg.Nobitz.AP.105536_TMYx.zip",
        "DEU_BB_Potsdam_103790_TRY2035_04_Somm_BBSR.zip",
        "DEU_BY_Nurnberg.AP.107630_TMYx.2007-2021.zip",
        "DEU_NI_Landeplatz.Meppen.AP.103040_TMYx.2004-2018.zip",
        "DEU_NI_Rotenburg.AP.102340_TMYx.2009-2023.zip",
        "DEU_NW_Paenbruch.104330_TMYx.2004-2018.zip",
        "DEU_BW_Messstetten.108270_TMYx.2004-2018.zip",
        "DEU_BW_Mannheim.107290_TMYx.zip",
        "DEU_BY_Wurzburg.106550_TMYx.zip",
        "DEU_NW_Koln.Bonn.AP.105130_TMYx.zip",
        "DEU_BY_Furstenzell.108950_TMYx.zip",
        "DEU_BW_Ohringen.107420_TMYx.zip",
        "DEU_BY_Siegenburg.108620_TMYx.zip",
        "DEU_HB_Borkumriff.Lightship.100020_TMYx.zip",
        "DEU_NI_Braunlage_104520_TRY2010_08_Somm_BBSR.zip",
        "DEU_SN_Leipzig.Halle.AP.104690_TMYx.2004-2018.zip",
        "DEU_SH_Hohenlockstedt-Itzehoe.Hungriger.Wolf.AP.101420_TMYx.2004-2018.zip",
        "DEU_HE_Fulda.105360_TMYx.zip",
        "DEU_NI_Oldenburg.102150_TMYx.2007-2021.zip",
        "DEU_BE_Berlin-Tempelhof.AP.103840_TMYx.zip",
        "DEU_NW_Hopsten.AP.103140_TMYx.zip",
        "DEU_BY_Greiling.AF.109710_TMYx.zip",
        "DEU_NW_Geilenkirchen.AFB.105000_TMYx.2009-2023.zip",
        "DEU_HE_Frankfurt.AP.106370_TMYx.zip",
        "DEU_BW_Stotten-Geislingen.an.der.Steige_108360_TRY2035_14_Jahr_BBSR.zip",
        "DEU_BW_Stuttgart.AP.107380_TMYx.2004-2018.zip",
        "DEU_NI_Cuxhaven.Nordholz.AP.101360_TMYx.zip",
        "DEU_SN_Goerlitz.AF.104990_TMYx.zip",
        "DEU_RP_Pirmasens.107170_TMYx.zip",
        "DEU_MV_Basepohl.102730_TMYx.zip",
        "DEU_NW_Achum.Buckeburg.AB.103350_TMYx.2007-2021.zip",
        "DEU_SH_Leck.AP.100220_TMYx.zip",
        "DEU_BY_Grafenwohr.AB.106870_TMYx.zip",
        "DEU_BW_Lahr-Schwarzwald.AP.108050_TMYx.zip",
        "DEU_BY_Hof.106850_TMYx.zip",
        "DEU_SH_Schleswig.AB.100370_TMYx.2009-2023.zip",
        "DEU_HB_Ahlhorn.AP.102180_TMYx.zip",
        "DEU_TH_Meiningen.105480_TMYx.zip",
        "DEU_TH_Gera.Leumnitz.AP.105670_TMYx.zip",
        "DEU_ST_Halle.Kroellwitz.104660_TMYx.zip",
        "DEU_NW_Luedenscheid.104180_TMYx.zip",
        "DEU_NI_Norderney.Island.101130_TMYx.zip",
        "DEU_NI_Luchow-Rehbeck.AP.102530_TMYx.zip",
        "DEU_NW_Aachen.105010_TMYx.zip",
        "DEU_SH_Kiel.Lighthouse.100440_TMYx.zip",
        "DEU_SH_Schleswig.AB.100370_TMYx.zip",
        "DEU_BW_Lechfeld.AB.108560_TMYx.2007-2021.zip",
        "DEU_NI_Cuxhaven.Nordholz.AP.101360_TMYx.2009-2023.zip",
        "DEU_BY_Ansbach.Katterbach.AB.107550_TMYx.2004-2018.zip",
        "DEU_NI_Wittmundhafen.AB.101260_TMYx.2004-2018.zip",
        "DEU_SH_Fehmar.100550_TMYx.2007-2021.zip",
        "DEU_BW_Messstetten.108270_TMYx.zip",
        "DEU_NI_Emden.AP.102000_TMYx.2007-2021.zip",
        "DEU_SL_Saarbrucken.AP.107080_TMYx.2007-2021.zip",
        "DEU_BY_Kummersbruck.107710_TMYx.2004-2018.zip",
        "DEU_BY_Regensburg-Oberhub.107760_TMYx.zip",
        "DEU_BY_Munich.AP.108700_TMYx.2007-2021.zip",
        "DEU_RP_Bad.Marienberg_105260_TRY2010_06_Jahr_BBSR.zip",
        "DEU_BY_Vilseck.AP.106595_TMYx.zip",
        "DEU_BY_Roth.AP.107650_TMYx.2004-2018.zip",
        "DEU_NW_Paderborn.Lippstadt.AP.104260_TMYx.2004-2018.zip",
        "DEU_BY_Altenstadt.AP.109540_TMYx.zip",
        "DEU_NW_Warburg.104350_TMYx.zip",
        "DEU_TH_Leinefelde.104490_TMYx.zip",
        "DEU_SH_Lubeck.AP.101560_TMYx.2007-2021.zip",
        "DEU_SH_Kiel.Kronshagen.100450_TMYx.zip",
        "DEU_MV_Boltenhagen.101610_TMYx.zip",
        "DEU_NI_Wunstorf.AB.103340_TMYx.2004-2018.zip",
        "DEU_NI_Jever.AB.101220_TMYx.zip",
        "DEU_NI_Braunschweig.103480_TMYx.2007-2021.zip",
        "DEU_MV_Greifswalder.Oie.100970_TMYx.2007-2021.zip",
        "DEU_BE_Berlin-Tegel.AP.103820_TMYx.2009-2023.zip",
        "DEU_TH_Grosser.Inselsberg.105490_TMYx.zip",
        "DEU_BW_Mannheim_107290_TRY2035_12_Jahr_BBSR.zip",
        "DEU_SH_Lubeck.AP.101560_TMYx.2009-2023.zip",
        "DEU_MV_Greifswald.101840_TMYx.zip",
        "DEU_MV_Rostock-Warnemunde_101700_TRY2010_02_Jahr_BBSR.zip",
        "DEU_SH_Hohenlockstedt-Itzehoe.Hungriger.Wolf.AP.101420_TMYx.zip",
        "DEU_HE_Geisenheim.106280_TMYx.2004-2018.zip",
        "DEU_BY_Furstenfeldbruck.AB.108580_TMYx.zip",
        "DEU_MV_Rostock-Laage.AP.101720_TMYx.2004-2018.zip",
        "DEU_NI_Hildesheim.AP.103370_TMYx.zip",
        "DEU_SH_Fehmar.100550_TMYx.zip",
        "DEU_BY_Breitsol.106450_TMYx.zip",
        "DEU_NI_Soltau.102350_TMYx.zip",
        "DEU_BB_Holzdorf.AB.104760_TMYx.zip",
        "DEU_BY_Munich-Theresienwiese.108650_TMYx.zip",
        "DEU_NW_Essen_104100_TRY2010_05_Somm_BBSR.zip",
        "DEU_BW_Stotten-Geislingen.an.der.Steige_108360_TRY2010_14_Somm_BBSR.zip",
        "DEU_SH_Kiel.Holtenau.AP.100460_TMYx.zip",
        "DEU_NI_Rotenburg.AP.102340_TMYx.zip",
        "DEU_NI_Wittmundhafen.AB.101260_TMYx.2007-2021.zip",
        "DEU_BW_Stuttgart-Schnarrenberg.107390_TMYx.zip",
        "DEU_BY_Feldkirchen-Mitterhausen.AF.107880_TMYx.zip",
        "DEU_BY_Nurnberg.AP.107630_TMYx.2004-2018.zip",
        "DEU_SH_Westerland.Sylt.AP.100180_TMYx.2004-2018.zip",
        "DEU_NW_Koterberg.104320_TMYx.zip",
        "DEU_NI_Jever.AB.101220_TMYx.2009-2023.zip",
        "DEU_BE_Berlin-Schonefeld.AP.103850_TMYx.2009-2023.zip",
        "DEU_SL_Berus.107040_TMYx.zip",
        "DEU_BY_Ansbach.Katterbach.AB.107550_TMYx.2007-2021.zip",
        "DEU_RP_Bad.Marienberg_105260_TRY2010_06_Wint_BBSR.zip",
        "DEU_NW_Norvenich.AP.105020_TMYx.2009-2023.zip",
        "DEU_BY_Weissenburg.107610_TMYx.zip",
        "DEU_BY_Hohenfels.AB.107750_TMYx.2009-2023.zip",
        "DEU_SH_Lubeck.AP.101560_TMYx.zip",
        "DEU_NI_Braunlage_104520_TRY2010_08_Wint_BBSR.zip",
        "DEU_HE_Frankfurt-Egelsbach.AP.106325_TMYx.2004-2018.zip",
        "DEU_SL_Saarbrucken.AP.107080_TMYx.2004-2018.zip",
        "DEU_NW_Monchengladbach.AP.104374_TMYx.2009-2023.zip",
        "DEU_NI_Lingen.103050_TMYx.zip",
        "DEU_BW_Sigmaringen.108280_TMYx.zip",
        "DEU_HE_Kleiner.Feldberg.106350_TMYx.zip",
        "DEU_BW_Karlsruhe-Baden-Baden.AP.107275_TMYx.2004-2018.zip",
        "DEU_NW_Weeze.AP.100001_TMYx.2007-2021.zip",
        "DEU_BW_Freudenstadt.108150_TMYx.zip",
        "DEU_BW_Penzing.AB.108570_TMYx.2007-2021.zip",
        "DEU_NW_Siegerland.AP.106162_TMYx.2004-2018.zip",
        "DEU_RP_Baumholder.AP.106190_TMYx.2007-2021.zip",
        "DEU_RP_Bad.Marienberg_105260_TRY2035_06_Somm_BBSR.zip",
        "DEU_HE_Frankfurt-Egelsbach.AP.106325_TMYx.2007-2021.zip",
        "DEU_HB_Bremerhaven_101290_TRY2035_01_Wint_BBSR.zip",
        "DEU_HE_Wasserkuppe.AP.105440_TMYx.zip",
        "DEU_HE_Kassel_104380_TRY2010_07_Wint_BBSR.zip",
        "DEU_RP_Bad.Marienberg_105260_TRY2035_06_Jahr_BBSR.zip",
        "DEU_BY_Zwiesel.107960_TMYx.zip",
        "DEU_BB_Potsdam_103790_TRY2010_04_Somm_BBSR.zip",
        "DEU_BY_Neuburg.AB.108530_TMYx.2004-2018.zip",
        "DEU_NW_Essen_104100_TRY2035_05_Wint_BBSR.zip",
        "DEU_MV_Neubrandenburg.Trollenhagen.AP.102810_TMYx.2007-2021.zip",
        "DEU_BW_Mannheim_107290_TRY2010_12_Wint_BBSR.zip",
        "DEU_RP_Sembach.AB.107120_TMYx.zip",
        "DEU_SN_Dresden.AP.104880_TMYx.zip",
        "DEU_TH_Neuhaus.105570_TMYx.zip",
        "DEU_RP_Nurburg.Barweiler.105060_TMYx.2007-2021.zip",
        "DEU_NW_Munster-Telgte.103130_TMYx.zip",
        "DEU_BY_Passau.108930_TMYx.zip",
        "DEU_RP_Buchel.AB.106130_TMYx.zip",
        "DEU_RP_Bad.Kreuznach.106270_TMYx.zip",
        "DEU_MV_Rostock-Laage.AP.101720_TMYx.2009-2023.zip",
        "DEU_SH_St.Peter.Ording.100280_TMYx.zip",
        "DEU_BY_Bamberg.106750_TMYx.zip",
        "DEU_RP_Idar.Oberstein.106180_TMYx.2007-2021.zip",
        "DEU_NW_Bonn.Roleber.105190_TMYx.zip",
        "DEU_HE_Kassel_104380_TRY2010_07_Jahr_BBSR.zip",
        "DEU_MV_Rostock-Warnemunde_101700_TRY2010_02_Somm_BBSR.zip",
        "DEU_NW_Gutersloh.AP.103200_TMYx.2009-2023.zip",
        "DEU_NI_Braunlage_104520_TRY2035_08_Somm_BBSR.zip",
        "DEU_NW_Gutersloh.AP.103200_TMYx.2007-2021.zip",
        "DEU_NI_Fassberg.AB.102460_TMYx.2004-2018.zip",
        "DEU_NW_Essen.DWD.104100_TMYx.zip",
        "DEU_HE_Wiesbaden.AB.106330_TMYx.2004-2018.zip",
        "DEU_BW_Schwabisch.Hall-Wurth.AP.107450_TMYx.2007-2021.zip",
        "DEU_BY_Leipheim.AP.108450_TMYx.zip",
        "DEU_BY_Ingolstadt.Manching.AF.108600_TMYx.2004-2018.zip",
        "DEU_RP_Bitburg.AB.106100_TMYx.zip",
        "DEU_BY_Chieming.109820_TMYx.zip",
        "DEU_HB_Bremen.AP.102240_TMYx.2009-2023.zip",
        "DEU_HE_Kassel.Calden.AP.104360_TMYx.2007-2021.zip",
        "DEU_SN_Chemnitz-Stelzendorf_105770_TRY2035_09_Somm_BBSR.zip",
        "DEU_BY_Oberstdorf.109480_TMYx.zip",
        "DEU_TH_Altenburg.Nobitz.AP.105536_TMYx.2009-2023.zip",
        "DEU_SH_List-Sylt.100200_TMYx.zip",
        "DEU_NI_Wunstorf.AB.103340_TMYx.2009-2023.zip",
        "DEU_NI_Rotenburg.AP.102340_TMYx.2007-2021.zip",
        "DEU_NI_Wittmundhafen.AB.101260_TMYx.2009-2023.zip",
        "DEU_BY_Ingolstadt.Manching.AF.108600_TMYx.2007-2021.zip",
        "DEU_SH_Eggebek.AB.100340_TMYx.zip",
        "DEU_BY_Erding.AB.108690_TMYx.2007-2021.zip",
        "DEU_BY_Kummersbruck.107710_TMYx.zip",
        "DEU_SN_Dresden.AP.104880_TMYx.2009-2023.zip",
        "DEU_BB_Weisen-Wittenberge.102620_TMYx.zip",
        "DEU_NW_Dortmund.AP.104160_TMYx.2007-2021.zip",
        "DEU_NI_Hannover.AP.103380_TMYx.2004-2018.zip",
        "DEU_NI_Landeplatz.Meppen.AP.103040_TMYx.zip",
        "DEU_BY_Hof_106850_TRY2010_10_Wint_BBSR.zip",
        "DEU_NW_Butzweilerhof.AFB.105090_TMYx.zip",
        "DEU_HE_Wahlen.105350_TMYx.zip",
        "DEU_HH_Hamburg-Schmidt.AP.101470_TMYx.2007-2021.zip",
        "DEU_BY_Oberpfaffenhofen.AB.108644_TMYx.2007-2021.zip",
        "DEU_HE_Frankfurt-Egelsbach.AP.106325_TMYx.zip",
        "DEU_BW_Laupheim.AB.108370_TMYx.2007-2021.zip",
        "DEU_HE_Michelstadt-Vielbrunn.106480_TMYx.zip",
        "DEU_BY_Grafenwohr.AB.106870_TMYx.2007-2021.zip",
        "DEU_RP_Frankfurt-Hahn.AP.106160_TMYx.2009-2023.zip",
        "DEU_BW_Sinsheim.AF.107350_TMYx.zip",
        "DEU_BW_Niederstetten.AP.107430_TMYx.2007-2021.zip",
        "DEU_RP_Weinbiet.107240_TMYx.zip",
        "DEU_BW_Niederstetten.AP.107430_TMYx.zip",
        "DEU_MV_Schwerin-Parchim.AP.101624_TMYx.2009-2023.zip",
        "DEU_BY_Munich.AP.108700_TMYx.2004-2018.zip",
        "DEU_SH_Meierwik.100330_TMYx.2007-2021.zip",
        "DEU_BY_Erding.AB.108690_TMYx.2009-2023.zip",
        "DEU_HB_Bremen.AP.102240_TMYx.zip",
        "DEU_NW_Weeze.AP.100001_TMYx.2009-2023.zip",
        "DEU_RP_Nurburg.105100_TMYx.zip",
        "DEU_HE_Fritzlar.AB.104390_TMYx.zip",
        "DEU_MV_Barth.101800_TMYx.zip",
        "DEU_BY_Furth.107620_TMYx.zip",
        "DEU_MV_Rostock-Laage.AP.101720_TMYx.2007-2021.zip",
        "DEU_BW_Mannheim.107290_TMYx.2009-2023.zip",
        "DEU_SH_Leck.AP.100220_TMYx.2004-2018.zip",
        "DEU_NI_Bergen.102380_TMYx.zip",
        "DEU_NW_Koln.Bonn.AP.105130_TMYx.2004-2018.zip",
        "DEU_BW_Donaueschingen-Villingen.AP.109120_TMYx.2004-2018.zip",
        "DEU_SH_Kiel.Holtenau.AP.100460_TMYx.2007-2021.zip",
        "DEU_MV_Marnitz.102640_TMYx.zip",
        "DEU_RP_Baumholder.AP.106598_TMYx.2009-2023.zip",
        "DEU_BY_Munich.AP.108700_TMYx.2009-2023.zip",
        "DEU_BB_Preschen.AP.104930_TMYx.zip",
        "DEU_BW_Coleman.AP.107280_TMYx.2009-2023.zip",
        "DEU_BW_Stuttgart-Weissenburg.107370_TMYx.zip",
        "DEU_HH_Hamburg-Schmidt.AP.101470_TMYx.2004-2018.zip",
        "DEU_BE_Berlin-Dahlem.103810_TMYx.zip",
        "DEU_BY_Oberpfaffenhofen.AB.108644_TMYx.2009-2023.zip",
        "DEU_RP_Ramstein.AFB.106140_TMYx.2007-2021.zip",
        "DEU_BY_Garmisch-Partenkirchen_109630_TRY2010_15_Wint_BBSR.zip",
        "DEU_RP_Bad.Marienberg_105260_TRY2035_06_Wint_BBSR.zip",
        "DEU_ST_Magdeburg.103610_TMYx.zip",
        "DEU_BW_Mannheim_107290_TRY2010_12_Jahr_BBSR.zip",
        "DEU_BW_Mannheim.107290_TMYx.2004-2018.zip",
        "DEU_NI_Celle.AP.103430_TMYx.2004-2018.zip",
        "DEU_HE_Langendiebach.AB.106420_TMYx.zip",
        "DEU_BY_Neuburg.AB.108530_TMYx.zip",
        "DEU_SH_Elpersbuttel.101300_TMYx.zip",
        "DEU_BW_Friedrichshafen.AP.109350_TMYx.2004-2018.zip",
        "DEU_SN_Chemnitz-Stelzendorf_105770_TRY2010_09_Jahr_BBSR.zip",
        "DEU_NW_Paderborn.Lippstadt.AP.104260_TMYx.2007-2021.zip",
        "DEU_HB_Diepholz.Dummerland.AP.103210_TMYx.2007-2021.zip",
        "DEU_BY_Giebelstadt.AP.106530_TMYx.zip",
        "DEU_RP_Zweibruecken.AP.107140_TMYx.zip",
        "DEU_BW_Muehlacker.107360_TMYx.zip",
        "DEU_SH_Westerland.Sylt.AP.100180_TMYx.zip",
        "DEU_MV_Neustrelitz.102790_TMYx.zip",
        "DEU_SH_Kiel.Holtenau.AP.100460_TMYx.2004-2018.zip",
        "DEU_NW_Dusseldorf.AP.104000_TMYx.2007-2021.zip",
        "DEU_RP_Traben.Trarbach.106170_TMYx.zip",
        "DEU_BY_Illesheim.AB.107520_TMYx.2009-2023.zip",
        "DEU_BY_Muhldorf.am.Inn_108750_TRY2035_13_Jahr_BBSR.zip",
        "DEU_NW_Weeze.AP.100001_TMYx.2004-2018.zip",
        "DEU_BY_Hof.106850_TMYx.2007-2021.zip",
        "DEU_NI_Oldenburg.102150_TMYx.2004-2018.zip",
        "DEU_BB_Potsdam_103790_TRY2035_04_Jahr_BBSR.zip",
        "DEU_BY_Wendelstein.Mtn.109800_TMYx.zip",
        "DEU_HB_Diepholz.Dummerland.AP.103210_TMYx.2004-2018.zip",
        "DEU_BY_Augsburg.AP.108520_TMYx.zip",
        "DEU_TH_Artern.104600_TMYx.zip",
        "DEU_BW_Laupheim.AB.108370_TMYx.2004-2018.zip",
        "DEU_NI_Fassberg.AB.102460_TMYx.2009-2023.zip",
        "DEU_NW_Werl.104240_TMYx.2004-2018.zip",
        "DEU_NW_Siegerland.AP.106162_TMYx.zip",
        "DEU_BY_Roth.AP.107650_TMYx.2009-2023.zip",
        "DEU_RP_Zweibruecken.AP.106163_TMYx.2007-2021.zip",
        "DEU_BY_Ansbach.Katterbach.AB.107550_TMYx.zip",
        "DEU_MV_Heringsdorf.AP.101920_TMYx.2009-2023.zip",
        "DEU_NW_Bocholt.104060_TMYx.zip",
        "DEU_RP_Frankfurt-Hahn.AP.106160_TMYx.2004-2018.zip",
        "DEU_SN_Fichtelberg_105780_TRY2035_11_Jahr_BBSR.zip",
        "DEU_HE_Kassel.Calden.AP.104360_TMYx.2009-2023.zip",
        "DEU_BW_Stotten-Geislingen.an.der.Steige_108360_TRY2035_14_Wint_BBSR.zip",
        "DEU_HE_Kassel_104380_TRY2035_07_Jahr_BBSR.zip",
        "DEU_NW_Koln.Bonn.AP.105130_TMYx.2007-2021.zip",
        "DEU_BY_Gelbelsee.107770_TMYx.zip",
        "DEU_BY_Memmingen-Allgau.AP.109470_TMYx.2007-2021.zip",
        "DEU_HE_Wiesbaden.AB.106330_TMYx.2007-2021.zip",
        "DEU_BY_Muhldorf.am.Inn_108750_TRY2010_13_Somm_BBSR.zip",
        "DEU_NI_Elbe.Lightship.100050_TMYx.zip",
        "DEU_BY_Hof.106850_TMYx.2004-2018.zip",
        "DEU_BY_Grosser.Arber.107910_TMYx.zip",
        "DEU_BW_Lechfeld.AB.108560_TMYx.2009-2023.zip",
        "DEU_BY_Bad.Kissingen.106580_TMYx.zip",
        "DEU_RP_Baumholder.AP.106190_TMYx.2009-2023.zip",
        "DEU_TH_Altenburg.Nobitz.AP.105536_TMYx.2004-2018.zip",
        "DEU_BW_Mannheim_107290_TRY2035_12_Wint_BBSR.zip",
        "DEU_HB_Bremerhaven_101290_TRY2010_01_Somm_BBSR.zip",
        "DEU_HB_Bremen.AP.102240_TMYx.2007-2021.zip",
        "DEU_BY_Ingolstadt.Manching.AF.108600_TMYx.2009-2023.zip",
        "DEU_SN_Zinnwald-Georgenfeld.105820_TMYx.zip",
        "DEU_BW_Stuttgart.AP.107380_TMYx.2007-2021.zip",
        "DEU_HH_Hamburg-Fuhlsbuttel_101470_TRY2035_03_Somm_BBSR.zip",
        "DEU_NI_Bremervoerde.101390_TMYx.zip",
        "DEU_TH_Weimar.105550_TMYx.zip",
        "DEU_RP_Nurburg.Barweiler.105060_TMYx.zip",
        "DEU_NI_Wunstorf.AB.103340_TMYx.2007-2021.zip",
        "DEU_BY_Hof_106850_TRY2035_10_Wint_BBSR.zip",
        "DEU_BY_Hohenfels.AB.107750_TMYx.zip",
        "DEU_NW_Bonn.Roleber.105190_TMYx.2007-2021.zip",
        "DEU_BB_Gruenow.102890_TMYx.zip",
        "DEU_SN_Leipzig.Halle.AP.104690_TMYx.2007-2021.zip",
        "DEU_HE_Frankfurt.AP.106370_TMYx.2009-2023.zip",
        "DEU_BB_Potsdam_103790_TRY2010_04_Jahr_BBSR.zip",
        "DEU_MV_Waren.102680_TMYx.2004-2018.zip",
        "DEU_BE_Berlin-Schonefeld.AP.103850_TMYx.2004-2018.zip",
        "DEU_BW_Donaueschingen-Villingen.AP.109120_TMYx.2009-2023.zip",
        "DEU_BY_Nurnberg.AP.107630_TMYx.zip",
        "DEU_NI_Hannover.AP.103380_TMYx.2009-2023.zip",
        "DEU_RP_Zweibruecken.AP.106163_TMYx.2009-2023.zip",
        "DEU_RP_Idar.Oberstein.106180_TMYx.2009-2023.zip",
        "DEU_BW_Niederstetten.AP.107430_TMYx.2009-2023.zip",
        "DEU_BY_Neubiberg.AB.108640_TMYx.zip",
        "DEU_BY_Munich.AP.108700_TMYx.zip",
        "DEU_SN_Fichtelberg_105780_TRY2010_11_Jahr_BBSR.zip",
        "DEU_ST_Salzwedel.102540_TMYx.zip",
        "DEU_BY_Hohenfels.AB.107750_TMYx.2004-2018.zip",
        "DEU_MV_Heringsdorf.AP.101920_TMYx.zip",
        "DEU_MV_Schwerin-Parchim.AP.101624_TMYx.2007-2021.zip",
        "DEU_NW_Achum.Buckeburg.AB.103350_TMYx.zip",
        "DEU_NI_Nordhorn.Lingen.AP.103080_TMYx.zip",
        "DEU_NI_Celle.AP.103430_TMYx.zip",
        "DEU_BE_Berlin-Tegel.AP.103820_TMYx.zip",
        "DEU_BB_Cottbus.AP.104920_TMYx.zip",
        "DEU_BY_Hohenfels.AB.107750_TMYx.2007-2021.zip",
        "DEU_MV_Heringsdorf.AP.101920_TMYx.2007-2021.zip",
        "DEU_SN_Leipzig.Holzhausen.104710_TMYx.zip",
        "DEU_MV_Schwerin-Parchim.AP.101624_TMYx.zip",
        "DEU_NW_Bruggen.AB.104010_TMYx.zip",
        "DEU_BB_Wittstock-Alt.Daber.AP.102720_TMYx.zip",
        "DEU_RP_Frankfurt-Hahn.AP.106160_TMYx.2007-2021.zip",
        "DEU_RP_Spangdahlem.AB.106070_TMYx.2009-2023.zip",
        "DEU_RP_Bad.Marienberg.105260_TMYx.zip",
        "DEU_SN_Fichtelberg_105780_TRY2035_11_Wint_BBSR.zip",
        "DEU_HB_Bremen.AP.102240_TMYx.2004-2018.zip",
        "DEU_BY_Ingolstadt.Manching.AF.108600_TMYx.zip",
        "DEU_BY_Garmisch-Partenkirchen_109630_TRY2035_15_Jahr_BBSR.zip",
        "DEU_BW_Heidelberg.AB.107340_TMYx.zip",
        "DEU_HE_Fritzlar.AB.104390_TMYx.2007-2021.zip",
        "DEU_SH_Hohenlockstedt-Itzehoe.Hungriger.Wolf.AP.101420_TMYx.2007-2021.zip",
        "DEU_BW_Lahr-Schwarzwald.AP.108050_TMYx.2007-2021.zip",
        "DEU_BY_Grafenwohr.AB.106870_TMYx.2004-2018.zip",
        "DEU_NI_Braunlage_104520_TRY2010_08_Jahr_BBSR.zip",
        "DEU_BW_Penzing.AB.108570_TMYx.2004-2018.zip",
        "DEU_BY_Bayreuth.AP.106770_TMYx.zip",
        "DEU_NI_Cuxhaven.101310_TMYx.zip",
        "DEU_BW_Goppingen.108354_TMYx.zip",
        "DEU_BY_Augsburg.AP.108520_TMYx.2007-2021.zip",
        "DEU_NI_Cuxhaven.Nordholz.AP.101360_TMYx.2004-2018.zip",
        "DEU_NI_Alte.Weser.Lighthouse.101240_TMYx.zip",
        "DEU_NI_Braunlage.104520_TMYx.zip",
        "DEU_NW_Norvenich.AP.105020_TMYx.2004-2018.zip",
        "DEU_NI_Wittmundhafen.AB.101260_TMYx.zip",
        "DEU_NW_Bad.Lippspringe.104300_TMYx.zip",
        "DEU_RP_Bendorf.105150_TMYx.zip",
        "DEU_BW_Schwabisch.Hall-Wurth.AP.107450_TMYx.zip",
        "DEU_BY_Altenstadt.AP.109540_TMYx.2009-2023.zip",
        "DEU_BY_Augsburg.AP.108520_TMYx.2009-2023.zip",
        "DEU_BY_Illesheim.AB.107520_TMYx.zip",
        "DEU_HE_Frankfurt-Egelsbach.AP.106325_TMYx.2009-2023.zip",
        "DEU_BW_Karlsruhe-Baden-Baden.AP.107275_TMYx.2009-2023.zip",
        "DEU_NW_Rheine.Bentlage.AP.103060_TMYx.zip",
        "DEU_NW_Munster.Osnabruck.AP.103150_TMYx.zip",
        "DEU_RP_Ramstein.AFB.106140_TMYx.2004-2018.zip",
        "DEU_NI_Wilhelmshaven.101270_TMYx.zip",
        "DEU_BW_Niederstetten.AP.107430_TMYx.2004-2018.zip",
        "DEU_SN_Chemnitz-Stelzendorf.105770_TMYx.zip",
        "DEU_NW_Dortmund.AP.104160_TMYx.zip",
        "DEU_ST_Brocken.104530_TMYx.zip",
        "DEU_BY_Roth.AP.107650_TMYx.2007-2021.zip",
        "DEU_NI_Fassberg.AB.102460_TMYx.2007-2021.zip",
        "DEU_BY_Hof_106850_TRY2010_10_Somm_BBSR.zip",
        "DEU_NW_Koln.Bonn.AP.105130_TMYx.2009-2023.zip",
        "DEU_RP_Spangdahlem.AB.106070_TMYx.2004-2018.zip",
        "DEU_NW_Dortmund.AP.104160_TMYx.2009-2023.zip",
        "DEU_HB_Bremerhaven_101290_TRY2010_01_Wint_BBSR.zip",
        "DEU_MV_Ueckermunde.101930_TMYx.zip",
        "DEU_NI_Cuxhaven.Nordholz.AP.101360_TMYx.2007-2021.zip",
        "DEU_NI_Braunlage_104520_TRY2035_08_Jahr_BBSR.zip",
        "DEU_BY_Muhldorf.am.Inn_108750_TRY2035_13_Wint_BBSR.zip",
        "DEU_BY_Neuburg.AB.108530_TMYx.2009-2023.zip",
        "DEU_BB_Potsdam.103790_TMYx.zip",
        "DEU_SN_Dresden.AP.104880_TMYx.2004-2018.zip",
        "DEU_SH_Meierwik.100330_TMYx.2009-2023.zip",
        "DEU_BW_Karlsruhe-Baden-Baden.AP.107275_TMYx.zip",
        "DEU_BW_Mannheim.107290_TMYx.2007-2021.zip",
        "DEU_NW_Bad.Salzuflen.103250_TMYx.zip",
        "DEU_BW_Stotten-Geislingen.an.der.Steige_108360_TRY2010_14_Wint_BBSR.zip",
        "DEU_BE_Berlin-Schonefeld.AP.103850_TMYx.2007-2021.zip",
        "DEU_BY_Memmingen-Allgau.AP.109470_TMYx.2009-2023.zip",
        "DEU_RP_Mendig.AP.105140_TMYx.zip",
        "DEU_SH_Kiel.Holtenau.AP.100460_TMYx.2009-2023.zip",
        "DEU_SN_Chemnitz-Stelzendorf_105770_TRY2010_09_Somm_BBSR.zip",
        "DEU_TH_Erfurt.Binderslebn.AP.105540_TMYx.2004-2018.zip",
        "DEU_MV_Parow.101810_TMYx.zip",
        "DEU_SH_Hohn.AB.100380_TMYx.2009-2023.zip",
        "DEU_BY_Hof_106850_TRY2035_10_Somm_BBSR.zip",
        "DEU_NI_Hannover.AP.103380_TMYx.zip",
        "DEU_SN_Fichtelberg.105780_TMYx.zip",
        "DEU_NW_Borgholzhausen.103180_TMYx.zip",
        "DEU_SH_Hohn.AB.100380_TMYx.2007-2021.zip",
        "DEU_NW_Munster.Osnabruck.AP.103150_TMYx.2007-2021.zip",
        "DEU_TH_Sonneberg-Neufang.105580_TMYx.zip",
        "DEU_BW_Stuttgart.AP.107380_TMYx.zip",
        "DEU_ST_Gardelegen.103590_TMYx.zip",
        "DEU_TH_Erfurt.Binderslebn.AP.105540_TMYx.zip",
        "DEU_NW_Essen_104100_TRY2010_05_Wint_BBSR.zip",
        "DEU_NW_Norvenich.AP.105020_TMYx.2007-2021.zip",
        "DEU_BE_Berlin-Tegel.AP.103820_TMYx.2004-2018.zip",
        "DEU_BY_Garmisch-Partenkirchen_109630_TRY2035_15_Wint_BBSR.zip",
        "DEU_BB_Angermunde.102910_TMYx.zip",
        "DEU_MV_Schwerin.101620_TMYx.zip",
        "DEU_BY_Garmisch-Partenkirchen_109630_TRY2010_15_Jahr_BBSR.zip",
        "DEU_NW_Luedenscheid.104180_TMYx.2007-2021.zip",
        "DEU_BY_Muhldorf.am.Inn_108750_TRY2035_13_Somm_BBSR.zip",
        "DEU_SN_Plauen.105690_TMYx.zip",
        "DEU_BY_Augsburg.AP.108520_TMYx.2004-2018.zip",
        "DEU_BY_Memmingen-Allgau.AP.109470_TMYx.zip",
        "DEU_SN_Wahnsdorf.104860_TMYx.zip",
        "DEU_SH_Doernick.101500_TMYx.zip",
        "DEU_BW_Karlsruhe.107270_TMYx.zip",
        "DEU_MV_Neubrandenburg.Trollenhagen.AP.102810_TMYx.zip",
        "DEU_HH_Hamburg-Fuhlsbuttel_101470_TRY2010_03_Wint_BBSR.zip",
        "DEU_NW_Weeze.AP.100001_TMYx.zip",
        "DEU_BW_Coleman.AP.107280_TMYx.zip",
        "DEU_BY_Muhldorf.AF.108750_TMYx.zip",
        "DEU_HE_Fritzlar.AB.104390_TMYx.2009-2023.zip",
        "DEU_RP_Nurburg.Barweiler.105060_TMYx.2004-2018.zip",
        "DEU_HE_Offenbach.Wetterpar.106410_TMYx.zip",
        "DEU_BY_Grafenwohr.AB.106870_TMYx.2009-2023.zip",
        "DEU_HE_Bad.Hersfeld.105420_TMYx.zip",
        "DEU_HH_Hamburg-Schmidt.AP.101470_TMYx.2009-2023.zip",
        "DEU_TH_Schmucke.105520_TMYx.zip",
        "DEU_RP_Idar.Oberstein.106180_TMYx.2004-2018.zip",
        "DEU_NW_Geilenkirchen.AFB.105000_TMYx.zip",
        "DEU_BW_Penzing.AB.108570_TMYx.2009-2023.zip",
        "DEU_NI_Braunschweig.103480_TMYx.2004-2018.zip",
        "DEU_NW_Essen_104100_TRY2035_05_Somm_BBSR.zip",
        "DEU_BW_Stotten-Geislingen.an.der.Steige_108360_TRY2010_14_Jahr_BBSR.zip",
        "DEU_SH_Neumunster.101430_TMYx.zip",
        "DEU_HE_Wiesbaden.AB.106330_TMYx.2009-2023.zip",
        "DEU_SH_Quickborn.101460_TMYx.zip",
        "DEU_SN_Oschatz.AP.104800_TMYx.zip",
        "DEU_BB_Neuruppin.102700_TMYx.zip",
        "DEU_SH_Dahmeshoved.101510_TMYx.zip",
        "DEU_SH_Quickborn.101460_TMYx.2007-2021.zip",
        "DEU_HE_Geisenheim.106280_TMYx.2007-2021.zip",
        "DEU_BW_Konstanz.109290_TMYx.zip",
        "DEU_NI_Hannover.AP.103380_TMYx.2007-2021.zip",
        "DEU_SH_Schleswig.AB.100370_TMYx.2004-2018.zip",
        "DEU_BW_Wertheim.106570_TMYx.zip",
        "DEU_BY_Altenstadt.AP.109540_TMYx.2007-2021.zip",
        "DEU_BY_Garmisch-Partenkirchen_109630_TRY2035_15_Somm_BBSR.zip",
        "DEU_HE_Geisenheim.106280_TMYx.zip",
        "DEU_RP_Frankfurt-Hahn.AP.106160_TMYx.zip",
        "DEU_NW_Dortmund.AP.104160_TMYx.2004-2018.zip",
        "DEU_NI_Wunstorf.AB.103340_TMYx.zip",
        "DEU_NI_Landeplatz.Meppen.AP.103040_TMYx.2007-2021.zip",
        "DEU_NW_Gutersloh.AP.103200_TMYx.2004-2018.zip",
        "DEU_BY_Oberpfaffenhofen.AB.108644_TMYx.zip",
        "DEU_BB_Doberlug.Kirchhain.104900_TMYx.zip",
        "DEU_BB_Potsdam_103790_TRY2010_04_Wint_BBSR.zip",
        "DEU_RP_Ramstein.AFB.106140_TMYx.zip",
        "DEU_SH_Westerland.Sylt.AP.100180_TMYx.2007-2021.zip",
        "DEU_MV_Boizenburg.102490_TMYx.zip",
        "DEU_RP_Pferdsfeld.AP.106260_TMYx.zip",
        "DEU_NW_Bonn.Roleber.105190_TMYx.2004-2018.zip",
        "DEU_SH_Pelzerhaken.101520_TMYx.zip",
        "DEU_SH_Schleswig.AB.100370_TMYx.2007-2021.zip",
        "DEU_NW_Werl.104240_TMYx.zip",
        "DEU_NI_Fassberg.AB.102460_TMYx.zip",
        "DEU_BY_Weiden.106880_TMYx.zip",
        "DEU_BW_Lechfeld.AB.108560_TMYx.zip",
        "DEU_MV_Rostock-Warnemunde_101700_TRY2035_02_Somm_BBSR.zip",
        "DEU_BW_Lechfeld.AB.108560_TMYx.2004-2018.zip",
        "DEU_BW_Karlsruhe-Baden-Baden.AP.107275_TMYx.2007-2021.zip",
        "DEU_BY_Ansbach.Katterbach.AB.107550_TMYx.2009-2023.zip",
        "DEU_NW_Paenbruch.104330_TMYx.2007-2021.zip",
        "DEU_RP_Idar.Oberstein.106180_TMYx.zip",
        "DEU_SL_Saarbrucken.AP.107080_TMYx.2009-2023.zip",
        "DEU_HH_Hamburg-Fuhlsbuttel_101470_TRY2010_03_Somm_BBSR.zip",
        "DEU_NI_Braunschweig.103480_TMYx.2009-2023.zip",
        "DEU_BW_Friedrichshafen.AP.109350_TMYx.2009-2023.zip",
        "DEU_TH_Erfurt.Binderslebn.AP.105540_TMYx.2009-2023.zip",
        "DEU_BE_Berlin-Tegel.AP.103820_TMYx.2007-2021.zip",
        "DEU_BW_Stuttgart.AP.107380_TMYx.2009-2023.zip",
        "DEU_NW_Paderborn.Lippstadt.AP.104260_TMYx.zip",
        "DEU_BW_Schnittlingen.108360_TMYx.zip",
        "DEU_BY_Hohenpeissenberg.Obs.109620_TMYx.zip",
        "DEU_BY_Hof_106850_TRY2035_10_Jahr_BBSR.zip",
        "DEU_RP_Buchel.AB.106130_TMYx.2004-2018.zip",
        "DEU_ST_Wernigerode.104540_TMYx.zip",
        "DEU_SN_Chemnitz-Stelzendorf_105770_TRY2035_09_Wint_BBSR.zip",
        "DEU_MV_Rostock-Warnemunde_101700_TRY2035_02_Wint_BBSR.zip",
        "DEU_BY_Muhldorf.am.Inn_108750_TRY2010_13_Wint_BBSR.zip",
        "DEU_SN_Dresden.AP.104880_TMYx.2007-2021.zip",
        "DEU_HH_Hamburg-Fuhlsbuttel_101470_TRY2010_03_Jahr_BBSR.zip",
        "DEU_SH_St.Peter.Ording.100280_TMYx.2007-2021.zip",
        "DEU_HH_Hamburg-Schmidt.AP.101470_TMYx.zip",
        "DEU_HE_Kassel.Calden.AP.104360_TMYx.zip",
        "DEU_HB_Diepholz.Dummerland.AP.103210_TMYx.zip",
        "DEU_BY_Weihenstephan.Durna.108630_TMYx.2007-2021.zip",
        "DEU_NW_Luedenscheid.104180_TMYx.2004-2018.zip",
        "DEU_BW_Ulm.108380_TMYx.zip",
        "DEU_RP_Buchel.AB.106130_TMYx.2009-2023.zip",
        "DEU_SH_St.Peter.Ording.100280_TMYx.2004-2018.zip",
        "DEU_NI_Bergen.102380_TMYx.2004-2018.zip",
        "DEU_TH_Altenburg.Nobitz.AP.105536_TMYx.2007-2021.zip",
        "DEU_TH_Kalteneber.104480_TMYx.zip",
        "DEU_MV_Heringsdorf.AP.101920_TMYx.2004-2018.zip",
        "DEU_SH_Marienleuchte-Puttgarden.100670_TMYx.zip",
        "DEU_ST_Seehausen.Altmark.102610_TMYx.zip",
        "DEU_BW_Schwabisch.Hall-Wurth.AP.107450_TMYx.2009-2023.zip",
        "DEU_MV_Greifswalder.Oie.100970_TMYx.zip",
        "DEU_RP_Bad.Marienberg_105260_TRY2010_06_Somm_BBSR.zip",
        "DEU_NW_Geilenkirchen.AFB.105000_TMYx.2007-2021.zip",
        "DEU_NW_Detmold.103280_TMYx.zip",
        "DEU_BW_Mannheim_107290_TRY2035_12_Somm_BBSR.zip",
        "DEU_BB_Brandenburg-Briest.AP.103700_TMYx.zip",
        "DEU_NI_Landeplatz.Meppen.AP.103040_TMYx.2009-2023.zip",
        "DEU_MV_Waren.102680_TMYx.2007-2021.zip",
        "DEU_RP_Ramstein.AFB.106140_TMYx.2009-2023.zip",
        "DEU_HB_Bremerhaven_101290_TRY2035_01_Somm_BBSR.zip",
        "DEU_MV_Rostock-Laage.AP.101720_TMYx.zip",
        "DEU_BY_Hof.106850_TMYx.2009-2023.zip",
        "DEU_NW_Monchengladbach.AP.104374_TMYx.2007-2021.zip",
        "DEU_SN_Fichtelberg_105780_TRY2010_11_Somm_BBSR.zip",
        "DEU_BY_Kummersbruck.107710_TMYx.2009-2023.zip",
        "DEU_TH_Kaltennordheim.105460_TMYx.zip",
        "DEU_HE_Fritzlar.AB.104390_TMYx.2004-2018.zip",
        "DEU_BY_Memmingen-Allgau.AP.109470_TMYx.2004-2018.zip",
        "DEU_SL_Tholey.107060_TMYx.zip",
        "DEU_NI_Bergen.102380_TMYx.2007-2021.zip",
        "DEU_NI_Emden.AP.102000_TMYx.zip",
        "DEU_BY_Mebstetten.Albstadt.106334_TMYx.zip",
        "DEU_NI_Celle.AP.103430_TMYx.2007-2021.zip",
        "DEU_BW_Baden.Oos.AP.107250_TMYx.zip",
        "DEU_BW_Mannheim_107290_TRY2010_12_Somm_BBSR.zip",
        "DEU_HB_Bremerhaven_101290_TRY2010_01_Jahr_BBSR.zip",
        "DEU_NI_Goettingen.104440_TMYx.zip",
        "DEU_BY_Erding.AB.108690_TMYx.zip",
        "DEU_BW_Lahr-Schwarzwald.AP.108050_TMYx.2004-2018.zip",
        "DEU_BY_Furstenzell.108950_TMYx.2007-2021.zip",
        "DEU_MV_Rostock-Warnemunde_101700_TRY2035_02_Jahr_BBSR.zip",
        "DEU_BW_Neuhausen.ob.Eck.AF.109210_TMYx.zip",
        "DEU_SH_Meierwik.100330_TMYx.2004-2018.zip",
        "DEU_MV_Rostock-Warnemunde_101700_TRY2010_02_Wint_BBSR.zip",
        "DEU_TH_Schleiz.105640_TMYx.zip",
        "DEU_HE_Maurice.Rose.106380_TMYx.zip",
        "DEU_BY_Nurnberg-Feucht.107640_TMYx.zip",
        "DEU_SH_Helgoland.Island.100150_TMYx.zip",
        "DEU_BW_Laupheim.AB.108370_TMYx.2009-2023.zip",
        "DEU_BW_Freiburg.AP.108030_TMYx.zip",
        "DEU_NW_Munster.Osnabruck.AP.103150_TMYx.2004-2018.zip",
        "DEU_NI_Bergen.102380_TMYx.2009-2023.zip",
        "DEU_NW_Kalkar.104040_TMYx.zip",
        "DEU_BY_Kitzingen.AP.106690_TMYx.zip",
        "DEU_NW_Munster.Osnabruck.AP.103150_TMYx.2009-2023.zip",
        "DEU_BW_Stotten-Geislingen.an.der.Steige_108360_TRY2035_14_Somm_BBSR.zip",
        "DEU_NW_Norvenich.AP.105020_TMYx.zip",
        "DEU_HE_Kassel_104380_TRY2035_07_Wint_BBSR.zip",
        "DEU_NI_Emden.AP.102000_TMYx.2009-2023.zip",
        "DEU_TH_Erfurt.Binderslebn.AP.105540_TMYx.2007-2021.zip",
        "DEU_HB_Bremerhaven_101290_TRY2035_01_Jahr_BBSR.zip",
        "DEU_BY_Garmisch-Partenkirchen.109630_TMYx.zip",
        "DEU_SN_Colomberg.104790_TMYx.zip",
        "DEU_BW_Coleman.AP.107280_TMYx.2007-2021.zip",
        "DEU_HH_Hamburg-Fuhlsbuttel_101470_TRY2035_03_Jahr_BBSR.zip",
        "DEU_HE_Kassel_104380_TRY2035_07_Somm_BBSR.zip",
        "DEU_MV_Greifswalder.Oie.100970_TMYx.2004-2018.zip",
        "DEU_BB_Trollenberg.Beeskow.103950_TMYx.zip",
        "DEU_HE_Frankfurt.Oder.103980_TMYx.zip",
        "DEU_HE_Langen.106390_TMYx.zip",
        "DEU_RP_Mainz-Finthen.AP.106320_TMYx.zip",
        "DEU_BY_Illesheim.AB.107520_TMYx.2004-2018.zip",
        "DEU_SH_Westerland.Sylt.AP.100180_TMYx.2009-2023.zip",
        "DEU_BY_Harburg.108500_TMYx.zip",
        "DEU_BY_Feldkirchen-Mitterhausen.AF.107880_TMYx.2004-2018.zip",
        "DEU_BY_Illesheim.AB.107520_TMYx.2007-2021.zip",
        "DEU_NW_Achum.Buckeburg.AB.103350_TMYx.2009-2023.zip",
        "DEU_BY_Lindenberg.103930_TMYx.zip",
        "DEU_SN_Leipzig.Halle.AP.104690_TMYx.zip",
        "DEU_HE_Kassel.Calden.AP.104360_TMYx.2004-2018.zip",
        "DEU_HH_Hamburg-Fuhlsbuttel_101470_TRY2035_03_Wint_BBSR.zip",
        "DEU_BY_Furstenzell.108950_TMYx.2004-2018.zip",
        "DEU_SH_Schleswig.100350_TMYx.zip",
        "DEU_NI_Braunschweig.103480_TMYx.zip",
        "DEU_HB_Diepholz.Dummerland.AP.103210_TMYx.2009-2023.zip",
        "DEU_BY_Kaufbeuren.AFB.109530_TMYx.zip",
        "DEU_BW_Messstetten.108270_TMYx.2009-2023.zip",
        "DEU_BW_Donaueschingen-Villingen.AP.109120_TMYx.zip",
        "DEU_MV_Cape.Arkona.100910_TMYx.zip",
        "DEU_RP_Baumholder.AP.106190_TMYx.zip",
        "DEU_SN_Leipzig.Holzhausen.104710_TMYx.2004-2018.zip",
        "DEU_BW_Penzing.AB.108570_TMYx.zip",
        "DEU_SH_Husum.Schwesing.AP.100260_TMYx.zip",
        "DEU_BB_Cottbus.104960_TMYx.zip",
        "DEU_BY_Weihenstephan.Durna.108630_TMYx.zip",
        "DEU_SH_Lubeck.AP.101560_TMYx.2004-2018.zip",
        "DEU_NW_Werl.104240_TMYx.2007-2021.zip",
        "DEU_SH_Quickborn.101460_TMYx.2004-2018.zip",
        "DEU_BY_Neuburg.AB.108530_TMYx.2007-2021.zip",
        "DEU_NI_Emden.AP.102000_TMYx.2004-2018.zip",
        "DEU_RP_Spangdahlem.AB.106070_TMYx.zip",
        "DEU_NW_Kahler.Asten.Mtn.104270_TMYx.zip",
        "DEU_NW_Paenbruch.104330_TMYx.zip",
        "DEU_HE_Kassel_104380_TRY2010_07_Somm_BBSR.zip",
        "DEU_NI_Celle.AP.103430_TMYx.2009-2023.zip",
        "DEU_BY_Feldkirchen-Mitterhausen.AF.107880_TMYx.2007-2021.zip",
        "DEU_RP_Trier-Petrisberg.106090_TMYx.zip",
        "DEU_NW_Rheine.Bentlage.AP.103060_TMYx.2009-2023.zip",
        "DEU_ST_Wittenberg.104740_TMYx.zip",
        "DEU_BB_Cottbus.Drewitz.AP.693664_TMYx.zip",
        "DEU_SN_Leipzig.Halle.AP.104690_TMYx.2009-2023.zip",
        "DEU_MV_Rostock-Warnemunde.101700_TMYx.zip",
        "DEU_RP_Baumholder.AP.106598_TMYx.zip",
        "DEU_NW_Rheine.Bentlage.AP.103060_TMYx.2004-2018.zip",
        "DEU_NI_Jever.AB.101220_TMYx.2007-2021.zip",
        "DEU_RP_Spangdahlem.AB.106070_TMYx.2007-2021.zip",
        "DEU_BW_Klippeneck.AF.108180_TMYx.zip",
        "DEU_MV_Waren.102680_TMYx.zip",
        "DEU_BY_Coburg-Lauteral-Oberlauter.106710_TMYx.zip",
        "DEU_BY_Oberpfaffenhofen.AB.108644_TMYx.2004-2018.zip",
        "DEU_BW_Feldberg.Schwarzwald.109080_TMYx.zip",
        "DEU_BB_Wiesenburg.103680_TMYx.zip",
        "DEU_NW_Siegerland.AP.106162_TMYx.2009-2023.zip",
        "DEU_NI_Braunlage_104520_TRY2035_08_Wint_BBSR.zip",
        "DEU_ST_Zugspitze.Mtn.109610_TMYx.zip",
        "DEU_BY_Kempten.109460_TMYx.zip",
        "DEU_BW_Bremgarten.AB.109000_TMYx.zip",
        "DEU_NW_Wildenrath.104020_TMYx.zip",
        "DEU_SH_Doernick.101500_TMYx.2004-2018.zip",
        "DEU_SH_Meierwik.100330_TMYx.zip",
        "DEU_BY_Kummersbruck.107710_TMYx.2007-2021.zip",
        "DEU_SN_Chemnitz-Stelzendorf_105770_TRY2010_09_Wint_BBSR.zip",
        "DEU_NW_Dusseldorf.AP.104000_TMYx.zip",
        "DEU_NI_Onsabruck.103170_TMYx.zip",
        "DEU_NW_Dusseldorf.AP.104000_TMYx.2004-2018.zip",
        "DEU_BW_Friedrichshafen.AP.109350_TMYx.zip",
        "DEU_MV_Schwerin-Parchim.AP.101624_TMYx.2004-2018.zip",
        "DEU_RP_Zweibruecken.AP.106163_TMYx.zip",
        "DEU_HH_Hamburg.Finkenwerder.AP.101490_TMYx.2007-2021.zip",
        "DEU_RP_Baumholder.AP.106598_TMYx.2007-2021.zip",
        "DEU_BW_Laupheim.AB.108370_TMYx.zip",
        "DEU_NW_Kalkar.104040_TMYx.2009-2023.zip",
        "DEU_SH_Schonhagen.100420_TMYx.zip",
        "DEU_SN_Fichtelberg_105780_TRY2035_11_Somm_BBSR.zip",
        "DEU_MV_Neubrandenburg.Trollenhagen.AP.102810_TMYx.2004-2018.zip",
        "DEU_SH_Hohn.AB.100380_TMYx.zip"
    ]
}